yeying/__init__.py
yeying/version.py
yeying/api/__init__.py
yeying/api/application/__init__.py
yeying/api/application/application_pb2.py
yeying/api/application/application_pb2.pyi
yeying/api/application/application_pb2_grpc.py
yeying/api/apps/__init__.py
yeying/api/apps/zuoyepigai/__init__.py
yeying/api/apps/zuoyepigai/archive_pb2.py
yeying/api/apps/zuoyepigai/archive_pb2.pyi
yeying/api/apps/zuoyepigai/archive_pb2_grpc.py
yeying/api/apps/zuoyepigai/assignment_pb2.py
yeying/api/apps/zuoyepigai/assignment_pb2.pyi
yeying/api/apps/zuoyepigai/assignment_pb2_grpc.py
yeying/api/apps/zuoyepigai/group_pb2.py
yeying/api/apps/zuoyepigai/group_pb2.pyi
yeying/api/apps/zuoyepigai/group_pb2_grpc.py
yeying/api/apps/zuoyepigai/homework_pb2.py
yeying/api/apps/zuoyepigai/homework_pb2.pyi
yeying/api/apps/zuoyepigai/homework_pb2_grpc.py
yeying/api/apps/zuoyepigai/imagecontent_pb2.py
yeying/api/apps/zuoyepigai/imagecontent_pb2.pyi
yeying/api/apps/zuoyepigai/imagecontent_pb2_grpc.py
yeying/api/apps/zuoyepigai/message_pb2.py
yeying/api/apps/zuoyepigai/message_pb2.pyi
yeying/api/apps/zuoyepigai/message_pb2_grpc.py
yeying/api/apps/zuoyepigai/meta_pb2.py
yeying/api/apps/zuoyepigai/meta_pb2.pyi
yeying/api/apps/zuoyepigai/meta_pb2_grpc.py
yeying/api/apps/zuoyepigai/mistakes_pb2.py
yeying/api/apps/zuoyepigai/mistakes_pb2.pyi
yeying/api/apps/zuoyepigai/mistakes_pb2_grpc.py
yeying/api/apps/zuoyepigai/task_pb2.py
yeying/api/apps/zuoyepigai/task_pb2.pyi
yeying/api/apps/zuoyepigai/task_pb2_grpc.py
yeying/api/apps/zuoyepigai/tasktag_pb2.py
yeying/api/apps/zuoyepigai/tasktag_pb2.pyi
yeying/api/apps/zuoyepigai/tasktag_pb2_grpc.py
yeying/api/apps/zuoyepigai/warehouse_pb2.py
yeying/api/apps/zuoyepigai/warehouse_pb2.pyi
yeying/api/apps/zuoyepigai/warehouse_pb2_grpc.py
yeying/api/asset/__init__.py
yeying/api/asset/asset_pb2.py
yeying/api/asset/asset_pb2.pyi
yeying/api/asset/asset_pb2_grpc.py
yeying/api/asset/block_pb2.py
yeying/api/asset/block_pb2.pyi
yeying/api/asset/block_pb2_grpc.py
yeying_client_python-0.1.0.dist-info/LICENSE
yeying_client_python-0.1.0.dist-info/METADATA
yeying_client_python-0.1.0.dist-info/WHEEL
yeying_client_python-0.1.0.dist-info/top_level.txt
yeying_client_python-0.1.0.dist-info/RECORD
