Metadata-Version: 2.1
Name: yeying-client-python
Version: 0.1.0
Summary: yeying python client
Home-page: https://github.com/yeying-community/yeying-client-python
Author: yeying-community
Author-email: your@email.com
License-File: LICENSE
